glacierbackup/__init__.py
glacierbackup/command.py
glacierbackup/database.py
glacierbackup/file_management.py
glacierbackup/init.py
glacierbackup/jobs.py
glacierbackup/misc.py
glacierbackup-0.1.0.dist-info/DESCRIPTION.rst
glacierbackup-0.1.0.dist-info/METADATA
glacierbackup-0.1.0.dist-info/RECORD
glacierbackup-0.1.0.dist-info/WHEEL
glacierbackup-0.1.0.dist-info/entry_points.txt
glacierbackup-0.1.0.dist-info/metadata.json
glacierbackup-0.1.0.dist-info/top_level.txt
