Metadata-Version: 2.0
Name: glacierbackup
Version: 0.1.0
Summary: A tool to track small files and back them up into Glacier enabling disaster-recovery document backups at virtually no cost
Home-page: https://github.com/arkhebuz/GlacierBackup
Author: Aleksander Tuzik
Author-email: aleksander.tuzik@gmail.com
License: MIT
Keywords: amazon,glacier,backup,aws
Platform: UNKNOWN
Classifier: Development Status :: 4 - Beta
Classifier: Environment :: Console
Classifier: Programming Language :: Python :: 3
Classifier: Topic :: System :: Archiving :: Backup
Classifier: License :: OSI Approved :: MIT License
Requires-Dist: boto3 (>=1.4.4)
Requires-Dist: pycryptodome (>=3.4.6)
